axes/__init__.py
axes/admin.py
axes/apps.py
axes/attempts.py
axes/backends.py
axes/checks.py
axes/conf.py
axes/decorators.py
axes/exceptions.py
axes/helpers.py
axes/middleware.py
axes/models.py
axes/signals.py
axes/utils.py
axes/handlers/__init__.py
axes/handlers/base.py
axes/handlers/cache.py
axes/handlers/database.py
axes/handlers/dummy.py
axes/handlers/proxy.py
axes/handlers/test.py
axes/locale/de/LC_MESSAGES/django.mo
axes/locale/de/LC_MESSAGES/django.po
axes/locale/pl/LC_MESSAGES/django.mo
axes/locale/pl/LC_MESSAGES/django.po
axes/locale/ru/LC_MESSAGES/django.mo
axes/locale/ru/LC_MESSAGES/django.po
axes/locale/tr/LC_MESSAGES/django.mo
axes/locale/tr/LC_MESSAGES/django.po
axes/management/__init__.py
axes/management/commands/__init__.py
axes/management/commands/axes_list_attempts.py
axes/management/commands/axes_reset.py
axes/management/commands/axes_reset_ip.py
axes/management/commands/axes_reset_logs.py
axes/management/commands/axes_reset_user.py
axes/management/commands/axes_reset_username.py
axes/migrations/0001_initial.py
axes/migrations/0002_auto_20151217_2044.py
axes/migrations/0003_auto_20160322_0929.py
axes/migrations/0004_auto_20181024_1538.py
axes/migrations/0005_remove_accessattempt_trusted.py
axes/migrations/0006_remove_accesslog_trusted.py
axes/migrations/0007_alter_accessattempt_unique_together.py
axes/migrations/__init__.py
django_axes_forked-5.27.1.dist-info/LICENSE
django_axes_forked-5.27.1.dist-info/METADATA
django_axes_forked-5.27.1.dist-info/WHEEL
django_axes_forked-5.27.1.dist-info/top_level.txt
django_axes_forked-5.27.1.dist-info/RECORD
