Metadata-Version: 2.1
Name: django-axes-forked
Version: 5.27.1
Summary: Keep track of failed login attempts in Django-powered sites.
Home-page: https://github.com/youssef3laa/django-axes/tree/fork-5.27.0
Author: Josh VanderLinden, Philip Neustrom, Michael Blume, Alex Clark, Camilo Nova, Aleksi Hakli
Author-email: security@jazzband.co
Maintainer: Jazzband
Maintainer-email: security@jazzband.co
License: MIT
Project-URL: Documentation, https://django-axes.readthedocs.io/
Project-URL: Source, https://github.com/jazzband/django-axes
Project-URL: Tracker, https://github.com/jazzband/django-axes/issues
Keywords: authentication django pci security
Platform: UNKNOWN
Classifier: Development Status :: 5 - Production/Stable
Classifier: Environment :: Web Environment
Classifier: Environment :: Plugins
Classifier: Framework :: Django
Classifier: Framework :: Django :: 2.2
Classifier: Framework :: Django :: 3.1
Classifier: Framework :: Django :: 3.2
Classifier: Intended Audience :: Developers
Classifier: Intended Audience :: System Administrators
Classifier: License :: OSI Approved :: MIT License
Classifier: Operating System :: OS Independent
Classifier: Programming Language :: Python
Classifier: Programming Language :: Python :: 3
Classifier: Programming Language :: Python :: 3.6
Classifier: Programming Language :: Python :: 3.7
Classifier: Programming Language :: Python :: 3.8
Classifier: Programming Language :: Python :: 3.9
Classifier: Programming Language :: Python :: 3.10
Classifier: Programming Language :: Python :: Implementation :: CPython
Classifier: Programming Language :: Python :: Implementation :: PyPy
Classifier: Topic :: Internet :: Log Analysis
Classifier: Topic :: Security
Classifier: Topic :: System :: Logging
Requires-Python: ~=3.6
License-File: LICENSE
Requires-Dist: django-ipware (<5,>=3)
Requires-Dist: django (>=2.2)
Requires-Dist: setuptools
